fbrefdata/__init__.py
fbrefdata/_common.py
fbrefdata/_config.py
fbrefdata/fbref.py
fbrefdata-0.3.0.dist-info/LICENSE.rst
fbrefdata-0.3.0.dist-info/METADATA
fbrefdata-0.3.0.dist-info/WHEEL
fbrefdata-0.3.0.dist-info/RECORD
