Metadata-Version: 2.1
Name: fbrefdata
Version: 0.3.0
Summary: A scraper of soccer data from FBref.
Home-page: https://github.com/lorenzodb1/fbrefdata
License: Apache-2.0
Keywords: fbref,soccer,football,soccer data,web scraping,soccer analytics
Author: Lorenzo De Bernardini
Author-email: lorenzo@envs.net
Requires-Python: >=3.9,<3.13
Classifier: License :: OSI Approved :: Apache Software License
Classifier: License :: OSI Approved :: MIT License
Classifier: Operating System :: OS Independent
Classifier: Programming Language :: Python :: 3
Classifier: Programming Language :: Python :: 3.9
Classifier: Programming Language :: Python :: 3.10
Classifier: Programming Language :: Python :: 3.11
Classifier: Programming Language :: Python :: 3.12
Requires-Dist: PySocks (>=1.7.1,<2.0.0)
Requires-Dist: Unidecode (>=1.2.0,<2.0.0)
Requires-Dist: html5lib (>=1.1,<2.0)
Requires-Dist: lxml (>=5.0.0,<6.0.0)
Requires-Dist: pandas (>=2.0.0,<3.0.0,!=2.1.0)
Requires-Dist: requests (>=2.23,<3.0)
Requires-Dist: rich (>=13.0.0,<14.0.0)
Requires-Dist: undetected-chromedriver (>=3.5.0,<4.0.0)
Requires-Dist: unicode (>=2.7,<3.0)
Project-URL: Repository, https://github.com/lorenzodb1/fbrefdata
